EasyMinecraftServer/__init__.py
EasyMinecraftServer/__main__.py
EasyMinecraftServer/data/software_list.py
EasyMinecraftServer/data/version_list.py
EasyMinecraftServer/main.py
easyminecraftserver-0.0.3.dist-info/entry_points.txt
easyminecraftserver-0.0.3.dist-info/LICENSE
easyminecraftserver-0.0.3.dist-info/METADATA
easyminecraftserver-0.0.3.dist-info/WHEEL
easyminecraftserver-0.0.3.dist-info/RECORD
