Metadata-Version: 2.3
Name: EasyMinecraftServer
Version: 0.0.3
Summary: A Typer app that makes the creation process of a Minecraft Server easier!
License: GPL-3.0-only
Keywords: game,minecraft,game server,server,fabric,forge,neoforge,paper,purpur,spigot
Author: Nucceteere
Author-email: ruzgar@nucceteere.xyz
Requires-Python: >=3.11
Classifier: Development Status :: 4 - Beta
Classifier: Environment :: Console
Classifier: Intended Audience :: Information Technology
Classifier: Intended Audience :: System Administrators
Classifier: License :: OSI Approved :: GNU General Public License v3 (GPLv3)
Classifier: Natural Language :: English
Classifier: Natural Language :: Turkish
Classifier: Operating System :: Microsoft :: Windows
Classifier: Operating System :: POSIX
Classifier: Programming Language :: Python :: 3
Classifier: Programming Language :: Python :: 3.11
Classifier: Programming Language :: Python :: 3.12
Classifier: Programming Language :: Python :: 3.13
Classifier: Topic :: Games/Entertainment
Classifier: Topic :: Utilities
Requires-Dist: javaproperties (>=0.8.2,<0.9.0)
Requires-Dist: pathvalidate (>=3.2.3,<4.0.0)
Requires-Dist: psutil (>=7.0.0,<8.0.0)
Requires-Dist: requests (>=2.32.3,<3.0.0)
Requires-Dist: typer (>=0.15.2,<0.16.0)
Project-URL: Bug Tracker, https://git.funtimes909.xyz/Nucceteere/EasyMinecraftServer/issues
Project-URL: Contribute, https://git.funtimes909.xyz/Nucceteere/EasyMinecraftServer/pulls
Project-URL: Documentation, https://git.funtimes909.xyz/Nucceteere/EasyMinecraftServer/wiki/
Project-URL: Homepage, https://git.funtimes909.xyz/Nucceteere/EasyMinecraftServer/src/branch/main/README.md
Project-URL: Repository, https://git.funtimes909.xyz/Nucceteere/EasyMinecraftServer/
